obzai/__init__.py
obzai/client/__init__.py
obzai/client/obz_client.py
obzai/client/configs/__init__.py
obzai/client/configs/api_config.py
obzai/client/configs/logger_config.py
obzai/client/schemas/__init__.py
obzai/client/schemas/dataclasses.py
obzai/client/schemas/exceptions.py
obzai/client/schemas/types.py
obzai/client/services/__init__.py
obzai/client/services/auth_service.py
obzai/client/services/cache_service.py
obzai/client/services/project_service.py
obzai/client/services/upload_service.py
obzai/client/services/utils/__init__.py
obzai/client/services/utils/array_encoding.py
obzai/client/services/utils/task_handlers.py
obzai/data_inspection/__init__.py
obzai/data_inspection/extractors/__init__.py
obzai/data_inspection/extractors/deep_extrc.py
obzai/data_inspection/extractors/extractor.py
obzai/data_inspection/extractors/first_order_extrc.py
obzai/data_inspection/feature_pipeline/__init__.py
obzai/data_inspection/feature_pipeline/feature_pipeline.py
obzai/data_inspection/inspectors/__init__.py
obzai/data_inspection/inspectors/base_data_inspector.py
obzai/data_inspection/inspectors/gmm_inspector.py
obzai/data_inspection/inspectors/pca_rec_inspector.py
obzai/data_inspection/od_models/__init__.py
obzai/data_inspection/od_models/base_od_model.py
obzai/data_inspection/od_models/gmm_model.py
obzai/data_inspection/od_models/pca_rec_model.py
obzai/data_inspection/schemas/__init__.py
obzai/data_inspection/schemas/dataclasses.py
obzai/data_inspection/schemas/exceptions.py
obzai/data_inspection/schemas/types.py
obzai/utils/__init__.py
obzai/utils/image_utils.py
obzai/xai/__init__.py
obzai/xai/xai_utils.py
obzai/xai/eval/__init__.py
obzai/xai/eval/eval_tool.py
obzai/xai/postprocessing/__init__.py
obzai/xai/postprocessing/regionizer.py
obzai/xai/schemas/__init__.py
obzai/xai/schemas/eval_results.py
obzai/xai/schemas/exceptions.py
obzai/xai/schemas/xai_results.py
obzai/xai/tools/__init__.py
obzai/xai/tools/attention_map.py
obzai/xai/tools/cdam.py
obzai-0.2.3.dist-info/licenses/LICENSE
obzai-0.2.3.dist-info/METADATA
obzai-0.2.3.dist-info/WHEEL
obzai-0.2.3.dist-info/top_level.txt
obzai-0.2.3.dist-info/RECORD
